nxpy_maven-1.0.3-py3.13-nspkg.pth
nxpy/maven/__init__.py
nxpy/maven/artifact.py
nxpy/maven/assembly_descriptor.py
nxpy/maven/mvn.py
nxpy/maven/pom.py
nxpy_maven-1.0.3.dist-info/LICENSE.txt
nxpy_maven-1.0.3.dist-info/METADATA
nxpy_maven-1.0.3.dist-info/WHEEL
nxpy_maven-1.0.3.dist-info/namespace_packages.txt
nxpy_maven-1.0.3.dist-info/top_level.txt
nxpy_maven-1.0.3.dist-info/RECORD
