Metadata-Version: 2.2
Name: nxpy-maven
Version: 1.0.3
Summary: Utilities for the Maven build tool
Home-page: https://github.com/nmusatti/nxpy
Author: Nicola Musatti
Author-email: Nicola Musatti <nicola.musatti@gmail.com>
License: Boost Software License - Version 1.0 - August 17th, 2003
Project-URL: Documentation, https://nxpy.readthedocs.io/en/latest/
Project-URL: Homepage, https://github.com/nmusatti/nxpy
Project-URL: Source Code, https://github.com/nmusatti/nxpy
Classifier: Development Status :: 5 - Production/Stable
Classifier: Intended Audience :: Developers
Classifier: License :: OSI Approved :: Boost Software License 1.0 (BSL-1.0)
Classifier: Programming Language :: Python :: 2
Classifier: Programming Language :: Python :: 2.7
Classifier: Programming Language :: Python :: 3
Classifier: Programming Language :: Python :: 3.5
Classifier: Programming Language :: Python :: 3.6
Classifier: Programming Language :: Python :: 3.7
Classifier: Programming Language :: Python :: 3.8
Classifier: Topic :: Software Development :: Libraries
License-File: LICENSE.txt
Requires-Dist: lxml
Requires-Dist: nxpy_command
Requires-Dist: nxpy_core
Requires-Dist: nxpy_sequence
Requires-Dist: nxpy_xml
Requires-Dist: six
Dynamic: author
Dynamic: home-page
